imhist.py
imhist-0.0.4.dist-info/LICENSE
imhist-0.0.4.dist-info/METADATA
imhist-0.0.4.dist-info/WHEEL
imhist-0.0.4.dist-info/top_level.txt
imhist-0.0.4.dist-info/RECORD
