Metadata-Version: 2.1
Name: imhist
Version: 0.0.4
Summary: This model calculates the histogram, PMF and CMD of a given matrix fast.
Home-page: https://github.com/Mamdasn/imhist
Author: mamdasn s
Author-email: <mamdassn@gmail.com>
License: UNKNOWN
Keywords: python,histogram,pmf,cdf,histogram of image
Platform: UNKNOWN
Classifier: Development Status :: 1 - Planning
Classifier: Intended Audience :: Science/Research
Classifier: License :: OSI Approved :: MIT License
Classifier: Programming Language :: Python :: 3.8
Classifier: Operating System :: OS Independent
